slack_blockkit/__init__.py
slack_blockkit/block.py
slack_blockkit/block_element.py
slack_blockkit/composition_object.py
slack_blockkit/layout_block.py
slack_blockkit/view_payload.py
slack_blockkit/utils/__init__.py
slack_blockkit/utils/blocks.py
slack_blockkit/utils/utils.py
sphinx/__init__.py
sphinx/conf.py
slack_blockkit-0.0.5.dist-info/LICENSE
slack_blockkit-0.0.5.dist-info/METADATA
slack_blockkit-0.0.5.dist-info/WHEEL
slack_blockkit-0.0.5.dist-info/top_level.txt
slack_blockkit-0.0.5.dist-info/RECORD
