Metadata-Version: 2.1
Name: slack-blockkit
Version: 0.0.5
Summary: Slack block kit builder for generating block messages programatically.
Home-page: https://github.com/ASU-CodeDevils/slack-blockkit
Author: Kevin Shelley
Author-email: webmaster@codedevils.org
License: MIT
Keywords: slack,blockkit,block,kit,block kit,api
Platform: UNKNOWN
Classifier: Development Status :: 4 - Beta
Classifier: Environment :: Web Environment
Classifier: Intended Audience :: Developers
Classifier: License :: OSI Approved :: MIT License
Classifier: Operating System :: OS Independent
Classifier: Programming Language :: Python
Classifier: Programming Language :: Python :: 3 :: Only
Classifier: Programming Language :: Python :: 3.5
Classifier: Programming Language :: Python :: 3.6
Classifier: Programming Language :: Python :: 3.7
Classifier: Programming Language :: Python :: 3.8
